sgis/__init__.py
sgis/conf.py
sgis/debug_config.py
sgis/exceptions.py
sgis/geopandas_tools/__init__.py
sgis/geopandas_tools/bounds.py
sgis/geopandas_tools/buffer_dissolve_explode.py
sgis/geopandas_tools/centerlines.py
sgis/geopandas_tools/cleaning.py
sgis/geopandas_tools/conversion.py
sgis/geopandas_tools/duplicates.py
sgis/geopandas_tools/general.py
sgis/geopandas_tools/geocoding.py
sgis/geopandas_tools/geometry_types.py
sgis/geopandas_tools/neighbors.py
sgis/geopandas_tools/overlay.py
sgis/geopandas_tools/point_operations.py
sgis/geopandas_tools/polygon_operations.py
sgis/geopandas_tools/polygons_as_rings.py
sgis/geopandas_tools/runners.py
sgis/geopandas_tools/sfilter.py
sgis/geopandas_tools/utils.py
sgis/helpers.py
sgis/io/__init__.py
sgis/io/_is_dapla.py
sgis/io/dapla_functions.py
sgis/io/opener.py
sgis/io/read_parquet.py
sgis/maps/__init__.py
sgis/maps/examine.py
sgis/maps/explore.py
sgis/maps/httpserver.py
sgis/maps/legend.py
sgis/maps/map.py
sgis/maps/maps.py
sgis/maps/norge_i_bilder.json
sgis/maps/thematicmap.py
sgis/maps/tilesources.py
sgis/maps/wms.py
sgis/networkanalysis/__init__.py
sgis/networkanalysis/_get_route.py
sgis/networkanalysis/_od_cost_matrix.py
sgis/networkanalysis/_points.py
sgis/networkanalysis/_service_area.py
sgis/networkanalysis/closing_network_holes.py
sgis/networkanalysis/cutting_lines.py
sgis/networkanalysis/directednetwork.py
sgis/networkanalysis/finding_isolated_networks.py
sgis/networkanalysis/network.py
sgis/networkanalysis/networkanalysis.py
sgis/networkanalysis/networkanalysisrules.py
sgis/networkanalysis/nodes.py
sgis/networkanalysis/traveling_salesman.py
sgis/parallel/__init__.py
sgis/parallel/parallel.py
sgis/py.typed
sgis/raster/__init__.py
sgis/raster/base.py
sgis/raster/image_collection.py
sgis/raster/indices.py
sgis/raster/regex.py
sgis/raster/sentinel_config.py
sgis/raster/zonal.py
ssb_sgis-1.3.6.dist-info/LICENSE
ssb_sgis-1.3.6.dist-info/METADATA
ssb_sgis-1.3.6.dist-info/WHEEL
ssb_sgis-1.3.6.dist-info/RECORD
