Metadata-Version: 2.1
Name: ssb-sgis
Version: 1.3.6
Summary: GIS functions used at Statistics Norway.
Home-page: https://github.com/statisticsnorway/ssb-sgis
License: MIT
Author: Morten Letnes
Author-email: morten.letnes@ssb.no
Requires-Python: >=3.11,<4
Classifier: Development Status :: 5 - Production/Stable
Classifier: License :: OSI Approved :: MIT License
Classifier: Programming Language :: Python :: 3
Classifier: Programming Language :: Python :: 3.11
Classifier: Programming Language :: Python :: 3.12
Classifier: Topic :: Scientific/Engineering :: GIS
Provides-Extra: all
Provides-Extra: bucket
Provides-Extra: test
Provides-Extra: xarray
Requires-Dist: affine (>=2.4.0)
Requires-Dist: branca (>=0.6.0)
Requires-Dist: dask (>=2024.1.1) ; extra == "all" or extra == "test"
Requires-Dist: folium (>=0.14.0)
Requires-Dist: gcsfs (>=2024.3.1) ; extra == "all" or extra == "bucket"
Requires-Dist: geopandas (>=0.14.0)
Requires-Dist: igraph (>=0.11.2)
Requires-Dist: ipython (>=8.13.2)
Requires-Dist: jenkspy (>=0.3.2)
Requires-Dist: jinja2 (>=3.1.3)
Requires-Dist: joblib (>=1.4.0)
Requires-Dist: mapclassify (>=2.5.0)
Requires-Dist: matplotlib (>=3.7.0)
Requires-Dist: networkx (>=3.0)
Requires-Dist: numpy (>=1.26.4)
Requires-Dist: pandas (>=2.0.1)
Requires-Dist: pyarrow (>=11.0.0)
Requires-Dist: pyproj (>=3.6.1)
Requires-Dist: rasterio (>=1.3.8)
Requires-Dist: requests (>=2.28.2)
Requires-Dist: rioxarray (>=0.15.5) ; extra == "all" or extra == "xarray" or extra == "test"
Requires-Dist: rtree (>=1.0.1)
Requires-Dist: scikit-learn (>=1.2.1)
Requires-Dist: shapely (>=2.0.1)
Requires-Dist: typing-extensions (>=4.11.0)
Requires-Dist: xarray (>=2024.3.0) ; extra == "all" or extra == "xarray" or extra == "test"
Requires-Dist: xyzservices (>=2023.2.0)
Project-URL: Changelog, https://github.com/statisticsnorway/ssb-sgis/releases
Project-URL: Documentation, https://statisticsnorway.github.io/ssb-sgis
Project-URL: Repository, https://github.com/statisticsnorway/ssb-sgis
